logback/__init__.py
logback/colorama/__init__.py
logback/colorama/ansi.py
logback/colorama/ansitowin32.py
logback/colorama/initialise.py
logback/colorama/win32.py
logback/colorama/winterm.py
logback-0.2.1.dist-info/METADATA
logback-0.2.1.dist-info/WHEEL
logback-0.2.1.dist-info/top_level.txt
logback-0.2.1.dist-info/RECORD
