Metadata-Version: 2.4
Name: logback
Version: 0.2.1
Summary: Log collection
Author: zjj
License: MIT
Requires-Python: >=3.9
